proalgotrader_core_binary/__init__.py
proalgotrader_core_binary/main.cpython-311-x86_64-linux-gnu.so
proalgotrader_core_binary/run.cpython-311-x86_64-linux-gnu.so
proalgotrader_core_binary/hello/__init__.py
proalgotrader_core_binary/hello/test.cpython-311-x86_64-linux-gnu.so
proalgotrader_core_binary-0.0.9b7.dist-info/LICENSE
proalgotrader_core_binary-0.0.9b7.dist-info/METADATA
proalgotrader_core_binary-0.0.9b7.dist-info/WHEEL
proalgotrader_core_binary-0.0.9b7.dist-info/top_level.txt
proalgotrader_core_binary-0.0.9b7.dist-info/RECORD
