Metadata-Version: 2.1
Name: proalgotrader-core-binary
Version: 0.0.9b7
Summary: ProAlgoTrader core
Home-page: https://github.com/krunaldodiya/proalgotrader_core_binary
Author: Krunal Dodiya
Author-email: kunal.dodiya1@gmail.com
Classifier: Programming Language :: Python :: 3
Classifier: Operating System :: OS Independent
License-File: LICENSE
Requires-Dist: wheel
Requires-Dist: twine
